helloworld.py
patrick_helloworld-0.0.2.dist-info/LICENSE.txt
patrick_helloworld-0.0.2.dist-info/METADATA
patrick_helloworld-0.0.2.dist-info/WHEEL
patrick_helloworld-0.0.2.dist-info/top_level.txt
patrick_helloworld-0.0.2.dist-info/RECORD
