Metadata-Version: 2.1
Name: patrick-helloworld
Version: 0.0.2
Summary: Say Hello!
Home-page: http://patrickold.me
Author: Patrick Old
Author-email: patrickold96@gmail.com
License: UNKNOWN
Platform: UNKNOWN
Classifier: Programming Language :: Python :: 3
Classifier: Programming Language :: Python :: 3.6
Classifier: Programming Language :: Python :: 3.7
Classifier: License :: OSI Approved :: MIT License
Classifier: Operating System :: OS Independent
Requires-Dist: blessings (~=1.7)
